{
	"name": "ds_output_adls2",
	"properties": {
		"linkedServiceName": {
			"referenceName": "ls_output_adls2",
			"type": "LinkedServiceReference"
		},
		"parameters": {
			"_file_name": {
				"type": "string"
			}
		},
		"annotations": [],
		"type": "DelimitedText",
		"typeProperties": {
			"location": {
				"type": "AzureBlobFSLocation",
				"fileName": {
					"value": "@dataset()._file_name",
					"type": "Expression"
				},
				"folderPath": "google",
				"fileSystem": "output"
			},
			"columnDelimiter": ",",
			"escapeChar": "\\",
			"firstRowAsHeader": true,
			"quoteChar": "\""
		},
		"schema": []
	},
	"type": "Microsoft.DataFactory/factories/datasets"
}